lumoscli.py
lumos/__init__.py
lumos/config.py
lumos/default_lumos_config.yaml
lumos/generator.py
lumos/logger.py
lumos/picasso.py
lumos/toolbox.py
lumos_cli-0.1.1.post1.dist-info/LICENCE.txt
lumos_cli-0.1.1.post1.dist-info/METADATA
lumos_cli-0.1.1.post1.dist-info/WHEEL
lumos_cli-0.1.1.post1.dist-info/entry_points.txt
lumos_cli-0.1.1.post1.dist-info/top_level.txt
lumos_cli-0.1.1.post1.dist-info/RECORD
