Metadata-Version: 2.1
Name: lumos-cli
Version: 0.1.1.post1
Summary: A cell painting plateviewer
Home-page: https://github.com/nicolasboisseau/lumos
Author: DSDM - Institut De Recherches Servier
Author-email: nicolas.boisseau@servier.com
License: MIT
Platform: UNKNOWN
Classifier: Programming Language :: Python :: 3.8
Classifier: Operating System :: OS Independent
Requires-Python: >=3.8
Requires-Dist: opencv-python (==4.5.4.60)
Requires-Dist: pandas (==1.3.5)
Requires-Dist: tqdm (==4.62.3)
Requires-Dist: click (==8.0.3)
Requires-Dist: art (==5.4)
Requires-Dist: PyYAML (==6.0)
